qtoggleserver/dallastemp/__init__.py
qtoggleserver/dallastemp/dallastemperaturesensor.py
qtoggleserver/dallastemp/ports.py
qtoggleserver_dallastemp-1.4.0.dist-info/licenses/LICENSE.txt
qtoggleserver_dallastemp-1.4.0.dist-info/METADATA
qtoggleserver_dallastemp-1.4.0.dist-info/WHEEL
qtoggleserver_dallastemp-1.4.0.dist-info/top_level.txt
qtoggleserver_dallastemp-1.4.0.dist-info/RECORD
