Metadata-Version: 2.4
Name: qtoggleserver-dallastemp
Version: 1.4.0
Summary: Dallas DS18B20 temperature sensor support for qToggleServer
Author-email: Calin Crisan <ccrisan@gmail.com>
License: Apache 2.0
Requires-Python: >=3.11
License-File: LICENSE.txt
Dynamic: license-file
